unimol_tools/__init__.py
unimol_tools/predict.py
unimol_tools/predictor.py
unimol_tools/train.py
unimol_tools/cli/__init__.py
unimol_tools/cli/run_predict.py
unimol_tools/cli/run_pretrain.py
unimol_tools/cli/run_repr.py
unimol_tools/cli/run_train.py
unimol_tools/config/__init__.py
unimol_tools/config/default.yaml
unimol_tools/config/model_config.py
unimol_tools/config/predict_config.yaml
unimol_tools/config/repr_config.yaml
unimol_tools/config/train_config.yaml
unimol_tools/data/__init__.py
unimol_tools/data/conformer.py
unimol_tools/data/datahub.py
unimol_tools/data/datareader.py
unimol_tools/data/datascaler.py
unimol_tools/data/dictionary.py
unimol_tools/data/split.py
unimol_tools/models/__init__.py
unimol_tools/models/loss.py
unimol_tools/models/nnmodel.py
unimol_tools/models/transformers.py
unimol_tools/models/transformersv2.py
unimol_tools/models/unimol.py
unimol_tools/models/unimolv2.py
unimol_tools/pretrain/__init__.py
unimol_tools/pretrain/data_utils.py
unimol_tools/pretrain/dataset.py
unimol_tools/pretrain/loss.py
unimol_tools/pretrain/metrics.py
unimol_tools/pretrain/preprocess.py
unimol_tools/pretrain/pretrain_config.py
unimol_tools/pretrain/trainer.py
unimol_tools/pretrain/unimol.py
unimol_tools/tasks/__init__.py
unimol_tools/tasks/trainer.py
unimol_tools/utils/__init__.py
unimol_tools/utils/base_logger.py
unimol_tools/utils/config_handler.py
unimol_tools/utils/dynamic_loss_scaler.py
unimol_tools/utils/metrics.py
unimol_tools/utils/util.py
unimol_tools/weights/__init__.py
unimol_tools/weights/weighthub.py
unimol_tools-0.1.5.dist-info/LICENSE
unimol_tools-0.1.5.dist-info/METADATA
unimol_tools-0.1.5.dist-info/WHEEL
unimol_tools-0.1.5.dist-info/top_level.txt
unimol_tools-0.1.5.dist-info/RECORD
