Metadata-Version: 2.1
Name: unimol-tools
Version: 0.1.5
Summary: unimol_tools is a Python package for property prediction with Uni-Mol in molecule, materials and protein.
Home-page: https://github.com/deepmodeling/unimol_tools
Author: DP Technology
Author-email: unimol@dp.tech
License: The MIT License
Classifier: Development Status :: 5 - Production/Stable
Classifier: Intended Audience :: Science/Research
Classifier: License :: OSI Approved :: Apache Software License
Classifier: Operating System :: POSIX :: Linux
Classifier: Programming Language :: Python :: 3.7
Classifier: Programming Language :: Python :: 3.8
Classifier: Programming Language :: Python :: 3.9
Classifier: Programming Language :: Python :: 3.10
Classifier: Topic :: Scientific/Engineering :: Artificial Intelligence
Requires-Python: >=3.9
License-File: LICENSE
Requires-Dist: numpy<2.3.0,>=2.0.0
Requires-Dist: pandas>=2.2.2
Requires-Dist: torch>=2.4.0
Requires-Dist: joblib
Requires-Dist: rdkit>=2024.3.4
Requires-Dist: pyyaml
Requires-Dist: addict
Requires-Dist: scikit-learn>=1.5.0
Requires-Dist: numba
Requires-Dist: tqdm
Requires-Dist: hydra-core
Requires-Dist: omegaconf
Requires-Dist: tensorboard
Requires-Dist: lmdb
